<?xml version="1.0" encoding="UTF-8"?>
<wps:ProcessDescriptions xmlns:wps="http://www.opengis.net/wps/1.0.0" xmlns:ows="http://www.opengis.net/ows/1.1" xmlns:xlink="http://www.w3.org/1999/xlink" xmlns:xsi="http://www.w3.org/2001/XMLSchema-instance" xsi:schemaLocation="http://www.opengis.net/wps/1.0.0
http://schemas.opengis.net/wps/1.0.0/wpsDescribeProcess_response.xsd" xml:lang="en-US" service="WPS" version="1.0.0">
	<ProcessDescription wps:processVersion="2" statusSupported="true" storeSupported="true">
		<ows:Identifier>org.n52.wps.ags.spatialanalyst.math.logical.isnull</ows:Identifier><!-- ParameterCount=2 -->	
		<ows:Title>IsNull_sa</ows:Title>
		<ows:Abstract>Returns 1 if the input value is NoData and 0 for cells that are not, on a cell-by-cell basis within the Analysis window. Uses ArcObjects library - Spatial Analyst</ows:Abstract>
		<DataInputs>
			<Input minOccurs="1" maxOccurs="1">
				<ows:Identifier>in_raster</ows:Identifier><!-- 0 -->
				<ows:Title>in raster</ows:Title>
				<ows:Abstract>The input being tested to identify the cells that are NoData (null).</ows:Abstract>
				<ComplexData>
					<Default>
						<Format>
							<MimeType>application/img</MimeType>
							<Schema></Schema>
						</Format>
					</Default>
					<Supported>
						<Format>
							<MimeType>application/GeoTIFF</MimeType>
							<Schema></Schema>
						</Format>
						<Format>
							<MimeType>application/img</MimeType>
							<Schema></Schema>
						</Format>	
					</Supported>
				</ComplexData>
			</Input>
		</DataInputs>
		<ProcessOutputs>
			<Output>
				<ows:Identifier>out_raster</ows:Identifier><!-- 1 -->
				<ows:Title>out raster</ows:Title>	
				<ows:Abstract>The output raster. Where cell values in the input are NoData, the output value will be 1. If it is any other value, the output value will be 0.</ows:Abstract>
				<ComplexOutput>
					<Default>
						<Format>
							<MimeType>application/img</MimeType>
							<Schema></Schema>
						</Format>
					</Default>
					<Supported>
						<Format>
							<MimeType>application/GeoTIFF</MimeType>
							<Schema></Schema>
						</Format>
						<Format>
							<MimeType>application/img</MimeType>
							<Schema></Schema>
						</Format>	
					</Supported>
				</ComplexOutput>
			</Output>
		</ProcessOutputs>
	</ProcessDescription>
</wps:ProcessDescriptions>
									
	