<?xml version="1.0" encoding="UTF-8"?>
<wps:ProcessDescriptions xmlns:wps="http://www.opengis.net/wps/1.0.0" xmlns:ows="http://www.opengis.net/ows/1.1" xmlns:xlink="http://www.w3.org/1999/xlink" xmlns:xsi="http://www.w3.org/2001/XMLSchema-instance" xsi:schemaLocation="http://www.opengis.net/wps/1.0.0
http://schemas.opengis.net/wps/1.0.0/wpsDescribeProcess_response.xsd" xml:lang="en-US" service="WPS" version="1.0.0">
	<ProcessDescription wps:processVersion="2" statusSupported="true" storeSupported="true">
		<ows:Identifier>org.n52.wps.ags.spatialanalyst.distance.corridor</ows:Identifier><!-- ParameterCount=3 -->		
		<ows:Title>Corridor_sa</ows:Title>
		<ows:Abstract>Calculates the sum of accumulative costs for two input accumulative cost raster. Uses ArcObjects library - Spatial Analyst</ows:Abstract>
		<DataInputs>
			<Input minOccurs="1" maxOccurs="1">
				<ows:Identifier>in_distance_raster1</ows:Identifier><!-- 0 -->
				<ows:Title>in distance raster1</ows:Title>
				<ows:Abstract>An input raster that was the output accumulated cost raster from a global cost function.</ows:Abstract>
				<ComplexData>
					<Default>
						<Format>
							<MimeType>application/img</MimeType>
							<Schema></Schema>
						</Format>
					</Default>
					<Supported>
						<Format>
							<MimeType>application/GeoTIFF</MimeType>
							<Schema></Schema>
						</Format>
						<Format>
							<MimeType>application/img</MimeType>
							<Schema></Schema>
						</Format>	
					</Supported>
				</ComplexData>
			</Input>
			<Input minOccurs="1" maxOccurs="1">
				<ows:Identifier>in_distance_raster2</ows:Identifier><!-- 1 -->
				<ows:Title>in distance raster2</ows:Title>
				<ows:Abstract>An input raster that was the output accumulated cost raster from a global cost function.</ows:Abstract>
				<ComplexData>
					<Default>
						<Format>
							<MimeType>application/img</MimeType>
							<Schema></Schema>
						</Format>
					</Default>
					<Supported>
						<Format>
							<MimeType>application/GeoTIFF</MimeType>
							<Schema></Schema>
						</Format>
						<Format>
							<MimeType>application/img</MimeType>
							<Schema></Schema>
						</Format>	
					</Supported>
				</ComplexData>
			</Input>
		</DataInputs>
		<ProcessOutputs>
			<Output>
				<ows:Identifier>out_raster</ows:Identifier><!-- 2 -->
				<ows:Title>out raster</ows:Title>	
				<ows:Abstract>The raster to be created.</ows:Abstract>
				<ComplexOutput>
					<Default>
						<Format>
							<MimeType>application/img</MimeType>
							<Schema></Schema>
						</Format>
					</Default>
					<Supported>
						<Format>
							<MimeType>application/GeoTIFF</MimeType>
							<Schema></Schema>
						</Format>
						<Format>
							<MimeType>application/img</MimeType>
							<Schema></Schema>
						</Format>	
					</Supported>
				</ComplexOutput>
			</Output>
		</ProcessOutputs>
	</ProcessDescription>
</wps:ProcessDescriptions>
									
	